{"cameraMode":{"drawMode":0,"name":"Shaded","section":"Shading Mode"},"sceneLighting":true,"audioPlay":false,"sceneViewState":{"m_AlwaysRefresh":false,"showFog":true,"showSkybox":true,"showFlares":true,"showImageEffects":true,"showParticleSystems":true,"showVisualEffectGraphs":true,"m_FxEnabled":true},"in2DMode":false,"pivot":{"x":-6.354020595550537,"y":14.168353080749512,"z":-2.3160207271575929},"rotation":{"x":-0.32786402106285097,"y":-0.1323307454586029,"z":0.04643941670656204,"w":-0.934281587600708},"size":13.778965950012207,"orthographic":false}